test_cj/__init__.py
test_cj/test.py
test_cj-0.1.dist-info/METADATA
test_cj-0.1.dist-info/WHEEL
test_cj-0.1.dist-info/top_level.txt
test_cj-0.1.dist-info/RECORD
