Metadata-Version: 2.1
Name: test-cj
Version: 0.1
Summary: for explain about pypi deploy
Home-page: https://github.com/qkdrk7777775/test_cj
Author: changje.cho
Author-email: qkdrk7777775@gmail.com
License: UNKNOWN
Download-URL: https://github.com/qkdrk7777775/test_cj/archive/master.zip
Keywords: pypi deploy
Platform: UNKNOWN
Classifier: Programming Language :: Python :: 3
Classifier: Programming Language :: Python :: 3.2
Classifier: Programming Language :: Python :: 3.3
Classifier: Programming Language :: Python :: 3.4
Classifier: Programming Language :: Python :: 3.5
Classifier: Programming Language :: Python :: 3.6
Classifier: Programming Language :: Python :: 3.7
Requires-Python: >=3
